AutoMLpy/__init__.py
AutoMLpy/logging_tools.py
AutoMLpy/tools.py
AutoMLpy/version.py
AutoMLpy/optimizers/__init__.py
AutoMLpy/optimizers/optimizer.py
AutoMLpy/parameter_generators/__init__.py
AutoMLpy/parameter_generators/gp_search.py
AutoMLpy/parameter_generators/grid_search.py
AutoMLpy/parameter_generators/parameter_generator.py
AutoMLpy/parameter_generators/random_search.py
AutoMLpy-0.0.31.dist-info/LICENSE.md
AutoMLpy-0.0.31.dist-info/METADATA
AutoMLpy-0.0.31.dist-info/WHEEL
AutoMLpy-0.0.31.dist-info/top_level.txt
AutoMLpy-0.0.31.dist-info/RECORD
