Metadata-Version: 2.1
Name: AutoMLpy
Version: 0.0.31
Summary: This package is an automatic machine learning module whose function is to optimize the hyper-parameters of an automatic learning model. Code at: https://github.com/JeremieGince/AutoMLpy .
Home-page: https://github.com/JeremieGince/AutoMLpy
Author: Jérémie Gince
Author-email: gincejeremie@gmail.com
License: Apache 2.0
Platform: UNKNOWN
Classifier: Programming Language :: Python :: 3
Classifier: License :: OSI Approved :: Apache Software License
Classifier: Operating System :: OS Independent
Requires-Python: >=3.6
Requires-Dist: wheel (>=0.36.2)
Requires-Dist: tqdm (>=4.56.0)
Requires-Dist: numpy (>=1.19.5)
Requires-Dist: scikit-learn (>=0.24.1)
Requires-Dist: scipy (>=1.6.0)
Requires-Dist: plotly (>=4.14.3)
Requires-Dist: pandas (>=1.2.1)
Requires-Dist: dash (>=1.19.0)
Requires-Dist: matplotlib (>=3.3.3)
Requires-Dist: psutil (>=5.8.0)
